example/cancel_invoice.py
example/request_transmitted_docs.py
example/send_invoice.py
mydata/__init__.py
mydata/client.py
mydata/client_config.py
mydata/exceptions.py
mydata/http_client.py
mydata/models/__init__.py
mydata/models/counterpart.py
mydata/models/invoice.py
mydata/models/invoices_document.py
mydata/models/issuer.py
mydata/models/payment_method_type.py
mydata/models/tax_type.py
mydata/models/vat_category.py
mydata/models/vat_exemption.py
mydata/models/withheld_percent_category.py
mydata/models/generated/__init__.py
mydata/models/generated/aade_book_invoice_type.py
mydata/models/generated/address_type.py
mydata/models/generated/cancelled_invoice_type.py
mydata/models/generated/continuation_token_type_1.py
mydata/models/generated/continuation_token_type_2.py
mydata/models/generated/continuation_token_type_3.py
mydata/models/generated/country_type.py
mydata/models/generated/currency_type.py
mydata/models/generated/ecrtoken_type.py
mydata/models/generated/entity_type.py
mydata/models/generated/error_type.py
mydata/models/generated/expenses_classification_category_type.py
mydata/models/generated/expenses_classification_type.py
mydata/models/generated/expenses_classification_value_type.py
mydata/models/generated/expenses_classifications_doc.py
mydata/models/generated/fuel_codes.py
mydata/models/generated/income_classification_category_type.py
mydata/models/generated/income_classification_type.py
mydata/models/generated/income_classification_value_type.py
mydata/models/generated/income_classifications_doc.py
mydata/models/generated/invoice_expenses_classification_type.py
mydata/models/generated/invoice_header_type.py
mydata/models/generated/invoice_income_classification_type.py
mydata/models/generated/invoice_provider_type.py
mydata/models/generated/invoice_row_type.py
mydata/models/generated/invoice_summary_type.py
mydata/models/generated/invoice_type.py
mydata/models/generated/invoice_vat_detail_type.py
mydata/models/generated/invoices_doc.py
mydatanaut-0.1.4.dist-info/licenses/LICENSE
mydatanaut-0.1.4.dist-info/METADATA
mydatanaut-0.1.4.dist-info/WHEEL
mydatanaut-0.1.4.dist-info/top_level.txt
mydatanaut-0.1.4.dist-info/RECORD
