Metadata-Version: 2.4
Name: mydatanaut
Version: 0.1.4
Summary: Python library for AADE myData REST API
Author-email: Thanos Theodoridis <at@atworks.gr>
License: MIT License
Project-URL: Homepage, https://github.com/attheodo/mydatanaut
Project-URL: Bug Tracker, https://github.com/attheodo/mydatanaut/issues
Keywords: AADE,myData,API
Classifier: Development Status :: 4 - Beta
Classifier: Intended Audience :: Developers
Classifier: Programming Language :: Python :: 3.10
Classifier: License :: OSI Approved :: MIT License
Classifier: Topic :: Software Development :: Libraries :: Python Modules
Requires-Python: >=3.10
License-File: LICENSE
Requires-Dist: requests
Requires-Dist: xsdata
Provides-Extra: dev
Requires-Dist: python-dotenv; extra == "dev"
Dynamic: license-file
